README.rst
setup.py
verb_counter/__init__.py
verb_counter/verb_counter.py
verb_counter.egg-info/PKG-INFO
verb_counter.egg-info/SOURCES.txt
verb_counter.egg-info/dependency_links.txt
verb_counter.egg-info/entry_points.txt
verb_counter.egg-info/requires.txt
verb_counter.egg-info/top_level.txt