Metadata-Version: 1.0
Name: verb-counter
Version: 1.2
Summary: UNKNOWN
Home-page: https://github.com/Ranc58/verbs_counter
Author: Vladimir Aleshin
Author-email: rancvova@gmail.com
License: MIT License
Platform: UNKNOWN
